Workbook

Sheet Orders
A1: order_id | B1: customer_id | C1: order_date | D1: product_id | E1: quantity | F1: sales_channel | G1: employee_id
A2: 5001 | B2: 101 | C2: 46027 | D2: P101 | E2: 1 | F2: Online | G2: E01
A3: 5002 | B3: 102 | C3: 46034 | D3: P102 | E3: 3 | F3: Store | G3: E03
A4: 5003 | B4: 103 | C4: 46042 | D4: P105 | E4: 2 | F4: Online | G4: E02
A5: 5004 | B5: 104 | C5: 46056 | D5: P103 | E5: 1 | F5: Store | G5: E03
A6: 5005 | B6: 105 | C6: 46068 | D6: P101 | E6: 2 | F6: Online | G6: E04
A7: 5006 | B7: 106 | C7: 46078 | D7: P106 | E7: 5 | F7: Online | G7: E01
A8: 5007 | B8: 107 | C8: 46083 | D8: P108 | E8: 1 | F8: Store | G8: E03
A9: 5008 | B9: 108 | C9: 46099 | D9: P104 | E9: 2 | F9: Store | G9: E01
A10: 5009 | B10: 109 | C10: 46109 | D10: P101 | E10: 1 | F10: Online | G10: E01
A11: 5010 | B11: 110 | C11: 46117 | D11: P107 | E11: 4 | F11: Online | G11: E05
A12: 5011 | B12: 101 | C12: 46127 | D12: P105 | E12: 1 | F12: Online | G12: E01
A13: 5012 | B13: 102 | C13: 46134 | D13: P103 | E13: 2 | F13: Store | G13: E03
... A31: 5030 | B31: 105 | C31: 46323 | D31: P105 | E31: 2 | F31: Online | G31: E04

Sheet Customers
A1: customer_id | B1: customer_name | C1: city | D1: country | E1: segment | F1: signup_date
A2: 101 | B2: Rahul | C2: Dubai | D2: UAE | E2: Premium | F2: 45306
A3: 102 | B3: Priya | C3: Chennai | D3: India | E3: Standard | F3: 45332
A4: 103 | B4: John | C4: Abu Dhabi | D4: UAE | E4: Premium | F4: 45356
A5: 104 | B5: Meena | C5: Bangalore | D5: India | E5: Standard | F5: 45402
A6: 105 | B6: Kiran | C6: Mumbai | D6: India | E6: Premium | F6: 45424
A7: 106 | B7: Kevin | C7: Dubai | D7: UAE | E7: Standard | F7: 45461
A8: 107 | B8: Alice | C8: Chennai | D8: India | E8: Premium | F8: 45495
A9: 108 | B9: Tom | C9: Sharjah | D9: UAE | E9: Standard | F9: 45518
A10: 109 | B10: Emma | C10: Dubai | D10: UAE | E10: Premium | F10: 45536
A11: 110 | B11: James | C11: Hyderabad | D11: India | E11: Standard | F11: 45576

Sheet Products
A1: product_id | B1: product_name | C1: category | D1: cost | E1: selling_price
A2: P101 | B2: Laptop | C2: Electronics | D2: 500 | E2: 700
A3: P102 | B3: Headphones | C3: Electronics | D3: 50 | E3: 90
A4: P103 | B4: Office Chair | C4: Furniture | D4: 100 | E4: 180
A5: P104 | B5: Desk | C5: Furniture | D5: 150 | E5: 250
A6: P105 | B6: Monitor | C6: Electronics | D6: 180 | E6: 280
A7: P106 | B7: Keyboard | C7: Accessories | D7: 30 | E7: 60
A8: P107 | B8: Mouse | C8: Accessories | D8: 20 | E8: 40
A9: P108 | B9: Printer | C9: Electronics | D9: 200 | E9: 320

Sheet Employees
A1: employee_id | B1: employee_name | C1: department | D1: city
A2: E01 | B2: Arun | C2: Sales | D2: Dubai
A3: E02 | B3: Meena | C3: Sales | D3: Abu Dhabi
A4: E03 | B4: David | C4: Sales | D4: Chennai
A5: E04 | B5: Sara | C5: Sales | D5: Mumbai
A6: E05 | B6: Kevin | C6: Sales | D6: Bangalore

Sheet Sales_Detail
A1: order_id | B1: customer_id | C1: order_date | D1: product_id | E1: quantity | F1: sales_channel | G1: employee_id | H1: product_name | I1: category | J1: cost | K1: selling_price | L1: customer_name | M1: city_x | N1: country | O1: segment | P1: signup_date | Q1: employee_name | R1: department | S1: city_y | T1: total_revenue | U1: total_cost | V1: total_profit | W1: month
A2: 5001 | B2: 101 | C2: 46027 | D2: P101 | E2: 1 | F2: Online | G2: E01 | H2: Laptop | I2: Electronics | J2: 500 | K2: 700 | L2: Rahul | M2: Dubai | N2: UAE | O2: Premium | P2: 45306 | Q2: Arun | R2: Sales | S2: Dubai | T2: =E2*K2 -> 700 | U2: =E2*J2 -> 500 | V2: =T2-U2 -> 200 | W2: =TEXT(C2,"YYYY-MM") -> 2026-01
A3: 5002 | B3: 102 | C3: 46034 | D3: P102 | E3: 3 | F3: Store | G3: E03 | H3: Headphones | I3: Electronics | J3: 50 | K3: 90 | L3: Priya | M3: Chennai | N3: India | O3: Standard | P3: 45332 | Q3: David | R3: Sales | S3: Chennai | T3: =E3*K3 -> 270 | U3: =E3*J3 -> 150 | V3: =T3-U3 -> 120 | W3: =TEXT(C3,"YYYY-MM") -> 2026-01
A4: 5003 | B4: 103 | C4: 46042 | D4: P105 | E4: 2 | F4: Online | G4: E02 | H4: Monitor | I4: Electronics | J4: 180 | K4: 280 | L4: John | M4: Abu Dhabi | N4: UAE | O4: Premium | P4: 45356 | Q4: Meena | R4: Sales | S4: Abu Dhabi | T4: =E4*K4 -> 560 | U4: =E4*J4 -> 360 | V4: =T4-U4 -> 200 | W4: =TEXT(C4,"YYYY-MM") -> 2026-01
A5: 5004 | B5: 104 | C5: 46056 | D5: P103 | E5: 1 | F5: Store | G5: E03 | H5: Office Chair | I5: Furniture | J5: 100 | K5: 180 | L5: Meena | M5: Bangalore | N5: India | O5: Standard | P5: 45402 | Q5: David | R5: Sales | S5: Chennai | T5: =E5*K5 -> 180 | U5: =E5*J5 -> 100 | V5: =T5-U5 -> 80 | W5: =TEXT(C5,"YYYY-MM") -> 2026-02
A6: 5005 | B6: 105 | C6: 46068 | D6: P101 | E6: 2 | F6: Online | G6: E04 | H6: Laptop | I6: Electronics | J6: 500 | K6: 700 | L6: Kiran | M6: Mumbai | N6: India | O6: Premium | P6: 45424 | Q6: Sara | R6: Sales | S6: Mumbai | T6: =E6*K6 -> 1400 | U6: =E6*J6 -> 1000 | V6: =T6-U6 -> 400 | W6: =TEXT(C6,"YYYY-MM") -> 2026-02
A7: 5006 | B7: 106 | C7: 46078 | D7: P106 | E7: 5 | F7: Online | G7: E01 | H7: Keyboard | I7: Accessories | J7: 30 | K7: 60 | L7: Kevin | M7: Dubai | N7: UAE | O7: Standard | P7: 45461 | Q7: Arun | R7: Sales | S7: Dubai | T7: =E7*K7 -> 300 | U7: =E7*J7 -> 150 | V7: =T7-U7 -> 150 | W7: =TEXT(C7,"YYYY-MM") -> 2026-02
A8: 5007 | B8: 107 | C8: 46083 | D8: P108 | E8: 1 | F8: Store | G8: E03 | H8: Printer | I8: Electronics | J8: 200 | K8: 320 | L8: Alice | M8: Chennai | N8: India | O8: Premium | P8: 45495 | Q8: David | R8: Sales | S8: Chennai | T8: =E8*K8 -> 320 | U8: =E8*J8 -> 200 | V8: =T8-U8 -> 120 | W8: =TEXT(C8,"YYYY-MM") -> 2026-03
A9: 5008 | B9: 108 | C9: 46099 | D9: P104 | E9: 2 | F9: Store | G9: E01 | H9: Desk | I9: Furniture | J9: 150 | K9: 250 | L9: Tom | M9: Sharjah | N9: UAE | O9: Standard | P9: 45518 | Q9: Arun | R9: Sales | S9: Dubai | T9: =E9*K9 -> 500 | U9: =E9*J9 -> 300 | V9: =T9-U9 -> 200 | W9: =TEXT(C9,"YYYY-MM") -> 2026-03
A10: 5009 | B10: 109 | C10: 46109 | D10: P101 | E10: 1 | F10: Online | G10: E01 | H10: Laptop | I10: Electronics | J10: 500 | K10: 700 | L10: Emma | M10: Dubai | N10: UAE | O10: Premium | P10: 45536 | Q10: Arun | R10: Sales | S10: Dubai | T10: =E10*K10 -> 700 | U10: =E10*J10 -> 500 | V10: =T10-U10 -> 200 | W10: =TEXT(C10,"YYYY-MM") -> 2026-03
A11: 5010 | B11: 110 | C11: 46117 | D11: P107 | E11: 4 | F11: Online | G11: E05 | H11: Mouse | I11: Accessories | J11: 20 | K11: 40 | L11: James | M11: Hyderabad | N11: India | O11: Standard | P11: 45576 | Q11: Kevin | R11: Sales | S11: Bangalore | T11: =E11*K11 -> 160 | U11: =E11*J11 -> 80 | V11: =T11-U11 -> 80 | W11: =TEXT(C11,"YYYY-MM") -> 2026-04
A12: 5011 | B12: 101 | C12: 46127 | D12: P105 | E12: 1 | F12: Online | G12: E01 | H12: Monitor | I12: Electronics | J12: 180 | K12: 280 | L12: Rahul | M12: Dubai | N12: UAE | O12: Premium | P12: 45306 | Q12: Arun | R12: Sales | S12: Dubai | T12: =E12*K12 -> 280 | U12: =E12*J12 -> 180 | V12: =T12-U12 -> 100 | W12: =TEXT(C12,"YYYY-MM") -> 2026-04
A13: 5012 | B13: 102 | C13: 46134 | D13: P103 | E13: 2 | F13: Store | G13: E03 | H13: Office Chair | I13: Furniture | J13: 100 | K13: 180 | L13: Priya | M13: Chennai | N13: India | O13: Standard | P13: 45332 | Q13: David | R13: Sales | S13: Chennai | T13: =E13*K13 -> 360 | U13: =E13*J13 -> 200 | V13: =T13-U13 -> 160 | W13: =TEXT(C13,"YYYY-MM") -> 2026-04
... A31: 5030 | B31: 105 | C31: 46323 | D31: P105 | E31: 2 | F31: Online | G31: E04 | H31: Monitor | I31: Electronics | J31: 180 | K31: 280 | L31: Kiran | M31: Mumbai | N31: India | O31: Premium | P31: 45424 | Q31: Sara | R31: Sales | S31: Mumbai | T31: =E31*K31 -> 560 | U31: =E31*J31 -> 360 | V31: =T31-U31 -> 200 | W31: =TEXT(C31,"YYYY-MM") -> 2026-10

Sheet Monthly_Summary
A1: month | B1: order_count | C1: total_quantity | D1: total_revenue | E1: total_cost | F1: total_profit | G1: profit_margin_pct | H1: revenue_growth_pct
A2: 2026-01 | B2: =COUNTIF(Sales_Detail!W2:W31,A2) -> 3 | C2: =SUMIF(Sales_Detail!W2:W31,A2,Sales_Detail!E2:E31) -> 6 | D2: =SUMIF(Sales_Detail!W2:W31,A2,Sales_Detail!T2:T31) -> 1530 | E2: =SUMIF(Sales_Detail!W2:W31,A2,Sales_Detail!U2:U31) -> 1010 | F2: =SUMIF(Sales_Detail!W2:W31,A2,Sales_Detail!V2:V31) -> 520 | G2: =IFERROR(F2/D2*100,0) -> 33.986928
A3: 2026-02 | B3: =COUNTIF(Sales_Detail!W2:W31,A3) -> 3 | C3: =SUMIF(Sales_Detail!W2:W31,A3,Sales_Detail!E2:E31) -> 8 | D3: =SUMIF(Sales_Detail!W2:W31,A3,Sales_Detail!T2:T31) -> 1880 | E3: =SUMIF(Sales_Detail!W2:W31,A3,Sales_Detail!U2:U31) -> 1250 | F3: =SUMIF(Sales_Detail!W2:W31,A3,Sales_Detail!V2:V31) -> 630 | G3: =IFERROR(F3/D3*100,0) -> 33.510638 | H3: =IFERROR((D3-D2)/D2*100,0) -> 22.875817
A4: 2026-03 | B4: =COUNTIF(Sales_Detail!W2:W31,A4) -> 3 | C4: =SUMIF(Sales_Detail!W2:W31,A4,Sales_Detail!E2:E31) -> 4 | D4: =SUMIF(Sales_Detail!W2:W31,A4,Sales_Detail!T2:T31) -> 1520 | E4: =SUMIF(Sales_Detail!W2:W31,A4,Sales_Detail!U2:U31) -> 1000 | F4: =SUMIF(Sales_Detail!W2:W31,A4,Sales_Detail!V2:V31) -> 520 | G4: =IFERROR(F4/D4*100,0) -> 34.210526 | H4: =IFERROR((D4-D3)/D3*100,0) -> -19.148936
A5: 2026-04 | B5: =COUNTIF(Sales_Detail!W2:W31,A5) -> 3 | C5: =SUMIF(Sales_Detail!W2:W31,A5,Sales_Detail!E2:E31) -> 7 | D5: =SUMIF(Sales_Detail!W2:W31,A5,Sales_Detail!T2:T31) -> 800 | E5: =SUMIF(Sales_Detail!W2:W31,A5,Sales_Detail!U2:U31) -> 460 | F5: =SUMIF(Sales_Detail!W2:W31,A5,Sales_Detail!V2:V31) -> 340 | G5: =IFERROR(F5/D5*100,0) -> 42.5 | H5: =IFERROR((D5-D4)/D4*100,0) -> -47.368421
A6: 2026-05 | B6: =COUNTIF(Sales_Detail!W2:W31,A6) -> 3 | C6: =SUMIF(Sales_Detail!W2:W31,A6,Sales_Detail!E2:E31) -> 8 | D6: =SUMIF(Sales_Detail!W2:W31,A6,Sales_Detail!T2:T31) -> 1810 | E6: =SUMIF(Sales_Detail!W2:W31,A6,Sales_Detail!U2:U31) -> 1150 | F6: =SUMIF(Sales_Detail!W2:W31,A6,Sales_Detail!V2:V31) -> 660 | G6: =IFERROR(F6/D6*100,0) -> 36.464088 | H6: =IFERROR((D6-D5)/D5*100,0) -> 126.25
A7: 2026-06 | B7: =COUNTIF(Sales_Detail!W2:W31,A7) -> 2 | C7: =SUMIF(Sales_Detail!W2:W31,A7,Sales_Detail!E2:E31) -> 4 | D7: =SUMIF(Sales_Detail!W2:W31,A7,Sales_Detail!T2:T31) -> 1200 | E7: =SUMIF(Sales_Detail!W2:W31,A7,Sales_Detail!U2:U31) -> 760 | F7: =SUMIF(Sales_Detail!W2:W31,A7,Sales_Detail!V2:V31) -> 440 | G7: =IFERROR(F7/D7*100,0) -> 36.666667 | H7: =IFERROR((D7-D6)/D6*100,0) -> -33.701657
A8: 2026-07 | B8: =COUNTIF(Sales_Detail!W2:W31,A8) -> 3 | C8: =SUMIF(Sales_Detail!W2:W31,A8,Sales_Detail!E2:E31) -> 9 | D8: =SUMIF(Sales_Detail!W2:W31,A8,Sales_Detail!T2:T31) -> 1940 | E8: =SUMIF(Sales_Detail!W2:W31,A8,Sales_Detail!U2:U31) -> 1280 | F8: =SUMIF(Sales_Detail!W2:W31,A8,Sales_Detail!V2:V31) -> 660 | G8: =IFERROR(F8/D8*100,0) -> 34.020619 | H8: =IFERROR((D8-D7)/D7*100,0) -> 61.666667
A9: 2026-08 | B9: =COUNTIF(Sales_Detail!W2:W31,A9) -> 3 | C9: =SUMIF(Sales_Detail!W2:W31,A9,Sales_Detail!E2:E31) -> 10 | D9: =SUMIF(Sales_Detail!W2:W31,A9,Sales_Detail!T2:T31) -> 2800 | E9: =SUMIF(Sales_Detail!W2:W31,A9,Sales_Detail!U2:U31) -> 1900 | F9: =SUMIF(Sales_Detail!W2:W31,A9,Sales_Detail!V2:V31) -> 900 | G9: =IFERROR(F9/D9*100,0) -> 32.142857 | H9: =IFERROR((D9-D8)/D8*100,0) -> 44.329897
A10: 2026-09 | B10: =COUNTIF(Sales_Detail!W2:W31,A10) -> 3 | C10: =SUMIF(Sales_Detail!W2:W31,A10,Sales_Detail!E2:E31) -> 6 | D10: =SUMIF(Sales_Detail!W2:W31,A10,Sales_Detail!T2:T31) -> 1340 | E10: =SUMIF(Sales_Detail!W2:W31,A10,Sales_Detail!U2:U31) -> 840 | F10: =SUMIF(Sales_Detail!W2:W31,A10,Sales_Detail!V2:V31) -> 500 | G10: =IFERROR(F10/D10*100,0) -> 37.313433 | H10: =IFERROR((D10-D9)/D9*100,0) -> -52.142857
A11: 2026-10 | B11: =COUNTIF(Sales_Detail!W2:W31,A11) -> 4 | C11: =SUMIF(Sales_Detail!W2:W31,A11,Sales_Detail!E2:E31) -> 8 | D11: =SUMIF(Sales_Detail!W2:W31,A11,Sales_Detail!T2:T31) -> 2370 | E11: =SUMIF(Sales_Detail!W2:W31,A11,Sales_Detail!U2:U31) -> 1510 | F11: =SUMIF(Sales_Detail!W2:W31,A11,Sales_Detail!V2:V31) -> 860 | G11: =IFERROR(F11/D11*100,0) -> 36.28692 | H11: =IFERROR((D11-D10)/D10*100,0) -> 76.865672

Sheet Product_Summary
A1: product_id | B1: product_name | C1: category | D1: order_count | E1: total_quantity | F1: total_revenue | G1: total_cost | H1: total_profit | I1: profit_margin_pct
A2: P101 | B2: Laptop | C2: Electronics | D2: =COUNTIF(Sales_Detail!D2:D31,A2) -> 7 | E2: =SUMIF(Sales_Detail!D2:D31,A2,Sales_Detail!E2:E31) -> 11 | F2: =SUMIF(Sales_Detail!D2:D31,A2,Sales_Detail!T2:T31) -> 7700 | G2: =SUMIF(Sales_Detail!D2:D31,A2,Sales_Detail!U2:U31) -> 5500 | H2: =F2-G2 -> 2200 | I2: =IFERROR(H2/F2*100,0) -> 28.571429
A3: P105 | B3: Monitor | C3: Electronics | D3: =COUNTIF(Sales_Detail!D2:D31,A3) -> 5 | E3: =SUMIF(Sales_Detail!D2:D31,A3,Sales_Detail!E2:E31) -> 10 | F3: =SUMIF(Sales_Detail!D2:D31,A3,Sales_Detail!T2:T31) -> 2800 | G3: =SUMIF(Sales_Detail!D2:D31,A3,Sales_Detail!U2:U31) -> 1800 | H3: =F3-G3 -> 1000 | I3: =IFERROR(H3/F3*100,0) -> 35.714286
A4: P104 | B4: Desk | C4: Furniture | D4: =COUNTIF(Sales_Detail!D2:D31,A4) -> 4 | E4: =SUMIF(Sales_Detail!D2:D31,A4,Sales_Detail!E2:E31) -> 10 | F4: =SUMIF(Sales_Detail!D2:D31,A4,Sales_Detail!T2:T31) -> 2500 | G4: =SUMIF(Sales_Detail!D2:D31,A4,Sales_Detail!U2:U31) -> 1500 | H4: =F4-G4 -> 1000 | I4: =IFERROR(H4/F4*100,0) -> 40
A5: P108 | B5: Printer | C5: Electronics | D5: =COUNTIF(Sales_Detail!D2:D31,A5) -> 3 | E5: =SUMIF(Sales_Detail!D2:D31,A5,Sales_Detail!E2:E31) -> 4 | F5: =SUMIF(Sales_Detail!D2:D31,A5,Sales_Detail!T2:T31) -> 1280 | G5: =SUMIF(Sales_Detail!D2:D31,A5,Sales_Detail!U2:U31) -> 800 | H5: =F5-G5 -> 480 | I5: =IFERROR(H5/F5*100,0) -> 37.5
A6: P103 | B6: Office Chair | C6: Furniture | D6: =COUNTIF(Sales_Detail!D2:D31,A6) -> 4 | E6: =SUMIF(Sales_Detail!D2:D31,A6,Sales_Detail!E2:E31) -> 6 | F6: =SUMIF(Sales_Detail!D2:D31,A6,Sales_Detail!T2:T31) -> 1080 | G6: =SUMIF(Sales_Detail!D2:D31,A6,Sales_Detail!U2:U31) -> 600 | H6: =F6-G6 -> 480 | I6: =IFERROR(H6/F6*100,0) -> 44.444444
A7: P102 | B7: Headphones | C7: Electronics | D7: =COUNTIF(Sales_Detail!D2:D31,A7) -> 3 | E7: =SUMIF(Sales_Detail!D2:D31,A7,Sales_Detail!E2:E31) -> 9 | F7: =SUMIF(Sales_Detail!D2:D31,A7,Sales_Detail!T2:T31) -> 810 | G7: =SUMIF(Sales_Detail!D2:D31,A7,Sales_Detail!U2:U31) -> 450 | H7: =F7-G7 -> 360 | I7: =IFERROR(H7/F7*100,0) -> 44.444444
A8: P106 | B8: Keyboard | C8: Accessories | D8: =COUNTIF(Sales_Detail!D2:D31,A8) -> 2 | E8: =SUMIF(Sales_Detail!D2:D31,A8,Sales_Detail!E2:E31) -> 11 | F8: =SUMIF(Sales_Detail!D2:D31,A8,Sales_Detail!T2:T31) -> 660 | G8: =SUMIF(Sales_Detail!D2:D31,A8,Sales_Detail!U2:U31) -> 330 | H8: =F8-G8 -> 330 | I8: =IFERROR(H8/F8*100,0) -> 50
A9: P107 | B9: Mouse | C9: Accessories | D9: =COUNTIF(Sales_Detail!D2:D31,A9) -> 2 | E9: =SUMIF(Sales_Detail!D2:D31,A9,Sales_Detail!E2:E31) -> 9 | F9: =SUMIF(Sales_Detail!D2:D31,A9,Sales_Detail!T2:T31) -> 360 | G9: =SUMIF(Sales_Detail!D2:D31,A9,Sales_Detail!U2:U31) -> 180 | H9: =F9-G9 -> 180 | I9: =IFERROR(H9/F9*100,0) -> 50

Sheet Channel_Summary
A1: sales_channel | B1: order_count | C1: total_quantity | D1: total_revenue | E1: total_cost | F1: total_profit | G1: average_order_value | H1: revenue_share_pct | I1: profit_margin_pct
A2: Online | B2: =COUNTIF(Sales_Detail!F2:F31,A2) -> 17 | C2: =SUMIF(Sales_Detail!F2:F31,A2,Sales_Detail!E2:E31) -> 38 | D2: =SUMIF(Sales_Detail!F2:F31,A2,Sales_Detail!T2:T31) -> 12000 | E2: =SUMIF(Sales_Detail!F2:F31,A2,Sales_Detail!U2:U31) -> 8130 | F2: =D2-E2 -> 3870 | G2: =IFERROR(D2/B2,0) -> 705.88235 | H2: =IFERROR(D2/SUM(D2:D3)*100,0) -> 69.808028 | I2: =IFERROR(F2/D2*100,0) -> 32.25
A3: Store | B3: =COUNTIF(Sales_Detail!F2:F31,A3) -> 13 | C3: =SUMIF(Sales_Detail!F2:F31,A3,Sales_Detail!E2:E31) -> 32 | D3: =SUMIF(Sales_Detail!F2:F31,A3,Sales_Detail!T2:T31) -> 5190 | E3: =SUMIF(Sales_Detail!F2:F31,A3,Sales_Detail!U2:U31) -> 3030 | F3: =D3-E3 -> 2160 | G3: =IFERROR(D3/B3,0) -> 399.23077 | H3: =IFERROR(D3/SUM(D2:D3)*100,0) -> 30.191972 | I3: =IFERROR(F3/D3*100,0) -> 41.618497

Sheet Dashboard_Data
A1: KPI | B1: Value | C1: Definition
A2: Total Orders | B2: =COUNTA(Orders!A2:A31) -> 30 | C2: Count of unique orders
A3: Total Revenue | B3: =SUM(Sales_Detail!T2:T31) -> 17190 | C3: Sum of quantity × selling price
A4: Total Cost | B4: =SUM(Sales_Detail!U2:U31) -> 11160 | C4: Sum of quantity × product cost
A5: Total Profit | B5: =SUM(Sales_Detail!V2:V31) -> 6030 | C5: Total revenue − total cost
A6: Overall Profit Margin (%) | B6: 35.08 | C6: Total profit ÷ total revenue × 100
A7: Average Order Value | B7: =IFERROR(B3/B2,0) -> 573 | C7: Total revenue ÷ unique orders
A8: Total Units Sold | B8: 70 | C8: Sum of quantities
A9: Customers | B9: 10 | C9: Unique customers in customer table
A10: Products | B10: 8 | C10: Unique products in product table

Sheet Category_Summary
A1: category | B1: total_revenue | C1: total_profit | D1: total_quantity | E1: profit_margin_pct
A2: Accessories | B2: =SUMIF(Sales_Detail!I2:I31,A2,Sales_Detail!T2:T31) -> 1020 | C2: =SUMIF(Sales_Detail!I2:I31,A2,Sales_Detail!V2:V31) -> 510 | D2: =SUMIF(Sales_Detail!I2:I31,A2,Sales_Detail!E2:E31) -> 20 | E2: =IFERROR(C2/B2*100,0) -> 50
A3: Electronics | B3: =SUMIF(Sales_Detail!I2:I31,A3,Sales_Detail!T2:T31) -> 12590 | C3: =SUMIF(Sales_Detail!I2:I31,A3,Sales_Detail!V2:V31) -> 4040 | D3: =SUMIF(Sales_Detail!I2:I31,A3,Sales_Detail!E2:E31) -> 34 | E3: =IFERROR(C3/B3*100,0) -> 32.088959
A4: Furniture | B4: =SUMIF(Sales_Detail!I2:I31,A4,Sales_Detail!T2:T31) -> 3580 | C4: =SUMIF(Sales_Detail!I2:I31,A4,Sales_Detail!V2:V31) -> 1480 | D4: =SUMIF(Sales_Detail!I2:I31,A4,Sales_Detail!E2:E31) -> 16 | E4: =IFERROR(C4/B4*100,0) -> 41.340782

Sheet City_Summary
A1: customer_city | B1: total_revenue | C1: total_profit | D1: order_count
A2: Abu Dhabi | B2: =SUMIF(Sales_Detail!M2:M31,A2,Sales_Detail!T2:T31) -> 1760 | C2: =SUMIF(Sales_Detail!M2:M31,A2,Sales_Detail!V2:V31) -> 600 | D2: =COUNTIF(Sales_Detail!M2:M31,A2) -> 3
A3: Bangalore | B3: =SUMIF(Sales_Detail!M2:M31,A3,Sales_Detail!T2:T31) -> 540 | C3: =SUMIF(Sales_Detail!M2:M31,A3,Sales_Detail!V2:V31) -> 260 | D3: =COUNTIF(Sales_Detail!M2:M31,A3) -> 2
A4: Chennai | B4: =SUMIF(Sales_Detail!M2:M31,A4,Sales_Detail!T2:T31) -> 2530 | C4: =SUMIF(Sales_Detail!M2:M31,A4,Sales_Detail!V2:V31) -> 920 | D4: =COUNTIF(Sales_Detail!M2:M31,A4) -> 6
A5: Dubai | B5: =SUMIF(Sales_Detail!M2:M31,A5,Sales_Detail!T2:T31) -> 5780 | C5: =SUMIF(Sales_Detail!M2:M31,A5,Sales_Detail!V2:V31) -> 2010 | D5: =COUNTIF(Sales_Detail!M2:M31,A5) -> 10
A6: Hyderabad | B6: =SUMIF(Sales_Detail!M2:M31,A6,Sales_Detail!T2:T31) -> 340 | C6: =SUMIF(Sales_Detail!M2:M31,A6,Sales_Detail!V2:V31) -> 160 | D6: =COUNTIF(Sales_Detail!M2:M31,A6) -> 2
A7: Mumbai | B7: =SUMIF(Sales_Detail!M2:M31,A7,Sales_Detail!T2:T31) -> 4810 | C7: =SUMIF(Sales_Detail!M2:M31,A7,Sales_Detail!V2:V31) -> 1500 | D7: =COUNTIF(Sales_Detail!M2:M31,A7) -> 4
A8: Sharjah | B8: =SUMIF(Sales_Detail!M2:M31,A8,Sales_Detail!T2:T31) -> 1430 | C8: =SUMIF(Sales_Detail!M2:M31,A8,Sales_Detail!V2:V31) -> 580 | D8: =COUNTIF(Sales_Detail!M2:M31,A8) -> 3

Sheet Customer_Summary
A1: customer_id | B1: customer_name | C1: order_count | D1: total_revenue | E1: total_profit
A2: 105 | B2: Kiran | C2: =COUNTIF(Sales_Detail!B2:B31,A2) -> 4 | D2: =SUMIF(Sales_Detail!B2:B31,A2,Sales_Detail!T2:T31) -> 4810 | E2: =SUMIF(Sales_Detail!B2:B31,A2,Sales_Detail!V2:V31) -> 1500
A3: 101 | B3: Rahul | C3: =COUNTIF(Sales_Detail!B2:B31,A3) -> 4 | D3: =SUMIF(Sales_Detail!B2:B31,A3,Sales_Detail!T2:T31) -> 2740 | E3: =SUMIF(Sales_Detail!B2:B31,A3,Sales_Detail!V2:V31) -> 860
A4: 109 | B4: Emma | C4: =COUNTIF(Sales_Detail!B2:B31,A4) -> 3 | D4: =SUMIF(Sales_Detail!B2:B31,A4,Sales_Detail!T2:T31) -> 2180 | E4: =SUMIF(Sales_Detail!B2:B31,A4,Sales_Detail!V2:V31) -> 740
A5: 103 | B5: John | C5: =COUNTIF(Sales_Detail!B2:B31,A5) -> 3 | D5: =SUMIF(Sales_Detail!B2:B31,A5,Sales_Detail!T2:T31) -> 1760 | E5: =SUMIF(Sales_Detail!B2:B31,A5,Sales_Detail!V2:V31) -> 600
A6: 107 | B6: Alice | C6: =COUNTIF(Sales_Detail!B2:B31,A6) -> 3 | D6: =SUMIF(Sales_Detail!B2:B31,A6,Sales_Detail!T2:T31) -> 1580 | E6: =SUMIF(Sales_Detail!B2:B31,A6,Sales_Detail!V2:V31) -> 520
A7: 108 | B7: Tom | C7: =COUNTIF(Sales_Detail!B2:B31,A7) -> 3 | D7: =SUMIF(Sales_Detail!B2:B31,A7,Sales_Detail!T2:T31) -> 1430 | E7: =SUMIF(Sales_Detail!B2:B31,A7,Sales_Detail!V2:V31) -> 580
A8: 102 | B8: Priya | C8: =COUNTIF(Sales_Detail!B2:B31,A8) -> 3 | D8: =SUMIF(Sales_Detail!B2:B31,A8,Sales_Detail!T2:T31) -> 950 | E8: =SUMIF(Sales_Detail!B2:B31,A8,Sales_Detail!V2:V31) -> 400
A9: 106 | B9: Kevin | C9: =COUNTIF(Sales_Detail!B2:B31,A9) -> 3 | D9: =SUMIF(Sales_Detail!B2:B31,A9,Sales_Detail!T2:T31) -> 860 | E9: =SUMIF(Sales_Detail!B2:B31,A9,Sales_Detail!V2:V31) -> 410
A10: 104 | B10: Meena | C10: =COUNTIF(Sales_Detail!B2:B31,A10) -> 2 | D10: =SUMIF(Sales_Detail!B2:B31,A10,Sales_Detail!T2:T31) -> 540 | E10: =SUMIF(Sales_Detail!B2:B31,A10,Sales_Detail!V2:V31) -> 260
A11: 110 | B11: James | C11: =COUNTIF(Sales_Detail!B2:B31,A11) -> 2 | D11: =SUMIF(Sales_Detail!B2:B31,A11,Sales_Detail!T2:T31) -> 340 | E11: =SUMIF(Sales_Detail!B2:B31,A11,Sales_Detail!V2:V31) -> 160

Sheet Formula_Guide
A1: Calculated field | B1: Formula example (Sales_Detail row 2) | C1: Purpose
A2: total_revenue | B2: E2*K2 | C2: Quantity × selling price
A3: total_cost | B3: E2*J2 | C3: Quantity × product cost
A4: total_profit | B4: T2-U2 | C4: Revenue − cost
A5: month | B5: =TEXT(C2,"YYYY-MM") -> Quantity × selling price | C5: Convert order date to year-month for monthly grouping
A6: Profit margin % | B6: IFERROR(total_profit/total_revenue*100,0) | C6: Profit as a percentage of revenue; use total profit ÷ total revenue
A7: Monthly revenue | B7: SUMIF($Sales_Detail.W2:W31,A2,$Sales_Detail.T2:T31) | C7: Sum revenue for the month in A2
A8: Orders per month | B8: COUNTIF($Sales_Detail.W2:W31,A2) | C8: Count order rows for a month
A9: Customer revenue | B9: SUMIF($Sales_Detail.B2:B31,A2,$Sales_Detail.T2:T31) | C9: Sum revenue for customer ID in A2
A10: Channel revenue share | B10: D2/SUM(D2:D3)*100 | C10: Channel revenue divided by total revenue
A11: Average order value | B11: total revenue/total orders | C11: Revenue divided by unique order count
